ps_screen.py
ps_screen-1.0.3.dist-info/METADATA
ps_screen-1.0.3.dist-info/WHEEL
ps_screen-1.0.3.dist-info/entry_points.txt
ps_screen-1.0.3.dist-info/top_level.txt
ps_screen-1.0.3.dist-info/RECORD
