Metadata-Version: 2.1
Name: ps-screen
Version: 1.0.3
Summary: List screen and tmux sessions and what's running in them.
Home-page: https://github.com/beaugunderson/ps-screen
Author: Beau Gunderson
Author-email: beau@beaugunderson.com
License: BSD
Keywords: utility ps screen tmux
Platform: UNKNOWN
Classifier: Environment :: Console
Classifier: Development Status :: 4 - Beta
Classifier: Intended Audience :: Developers
Classifier: Intended Audience :: End Users/Desktop
Classifier: Intended Audience :: Information Technology
Classifier: Intended Audience :: System Administrators
Classifier: License :: OSI Approved :: BSD License
Classifier: Operating System :: POSIX
Classifier: Operating System :: MacOS :: MacOS X
Classifier: Programming Language :: Python
Classifier: Topic :: Utilities
Requires-Dist: click (>=3.3)
Requires-Dist: psutil (>=2.1.3)
Requires-Dist: tabulate (>=0.7.3)
